ha_ssh_helpers/__init__.py
ha_ssh_helpers/base_entity.py
ha_ssh_helpers/binary_sensor.py
ha_ssh_helpers/button.py
ha_ssh_helpers/config_flow.py
ha_ssh_helpers/const.py
ha_ssh_helpers/converter.py
ha_ssh_helpers/coordinator.py
ha_ssh_helpers/helpers.py
ha_ssh_helpers/number.py
ha_ssh_helpers/select.py
ha_ssh_helpers/sensor.py
ha_ssh_helpers/switch.py
ha_ssh_helpers/text.py
ha_ssh_helpers-0.1.0.dist-info/LICENSE
ha_ssh_helpers-0.1.0.dist-info/METADATA
ha_ssh_helpers-0.1.0.dist-info/WHEEL
ha_ssh_helpers-0.1.0.dist-info/top_level.txt
ha_ssh_helpers-0.1.0.dist-info/RECORD
