Metadata-Version: 2.1
Name: ha-ssh-helpers
Version: 0.1.0
Summary: Helper module for the Home Assistant SSH integration
Author-email: zhbjsh <zhbjsh@outlook.com>
Project-URL: Homepage, https://github.com/zhbjsh/ha-ssh-helpers
Project-URL: Bug Tracker, https://github.com/zhbjsh/ha-ssh-helpers/issues
Classifier: Programming Language :: Python :: 3.10
Classifier: License :: OSI Approved :: MIT License
Classifier: Operating System :: OS Independent
Requires-Python: >=3.10
License-File: LICENSE
Requires-Dist: ssh-terminal-manager (>=0.9.2)
